LICENCE.txt
MANIFEST.in
README.rst
setup.py
Optimus_foundation.egg-info/PKG-INFO
Optimus_foundation.egg-info/SOURCES.txt
Optimus_foundation.egg-info/dependency_links.txt
Optimus_foundation.egg-info/not-zip-safe
Optimus_foundation.egg-info/requires.txt
Optimus_foundation.egg-info/top_level.txt
optimus_foundation/README.rst
optimus_foundation/__init__.py
optimus_foundation/gemsets.txt
optimus_foundation/requirements.txt
optimus_foundation/scripts/__init__.py.tpl
optimus_foundation/scripts/babel.cfg.tpl
optimus_foundation/scripts/config.rb.tpl
optimus_foundation/scripts/gitignore.tpl
optimus_foundation/scripts/pages.py.tpl
optimus_foundation/scripts/prod_settings.py.tpl
optimus_foundation/scripts/settings.py.tpl
optimus_foundation/sources/css/app.css
optimus_foundation/sources/images/foundation/orbit/bullets.jpg
optimus_foundation/sources/images/foundation/orbit/left-arrow-small.png
optimus_foundation/sources/images/foundation/orbit/left-arrow.png
optimus_foundation/sources/images/foundation/orbit/loading.gif
optimus_foundation/sources/images/foundation/orbit/mask-black.png
optimus_foundation/sources/images/foundation/orbit/pause-black.png
optimus_foundation/sources/images/foundation/orbit/right-arrow-small.png
optimus_foundation/sources/images/foundation/orbit/right-arrow.png
optimus_foundation/sources/images/foundation/orbit/rotator-black.png
optimus_foundation/sources/images/foundation/orbit/timer-black.png
optimus_foundation/sources/js/foundation/app.js
optimus_foundation/sources/js/foundation/jquery.cookie.js
optimus_foundation/sources/js/foundation/jquery.event.move.js
optimus_foundation/sources/js/foundation/jquery.event.swipe.js
optimus_foundation/sources/js/foundation/jquery.foundation.accordion.js
optimus_foundation/sources/js/foundation/jquery.foundation.alerts.js
optimus_foundation/sources/js/foundation/jquery.foundation.buttons.js
optimus_foundation/sources/js/foundation/jquery.foundation.clearing.js
optimus_foundation/sources/js/foundation/jquery.foundation.forms.js
optimus_foundation/sources/js/foundation/jquery.foundation.joyride.js
optimus_foundation/sources/js/foundation/jquery.foundation.magellan.js
optimus_foundation/sources/js/foundation/jquery.foundation.mediaQueryToggle.js
