Metadata-Version: 1.1
Name: Optimus-foundation
Version: 3.2.5.1
Summary: 
